README.md
setup.cfg
setup.py
bin/mympingpong.py
bin/mympingponganalysis.py
lib/mympingpong.egg-info/PKG-INFO
lib/mympingpong.egg-info/SOURCES.txt
lib/mympingpong.egg-info/dependency_links.txt
lib/mympingpong.egg-info/namespace_packages.txt
lib/mympingpong.egg-info/requires.txt
lib/mympingpong.egg-info/top_level.txt
lib/vsc/__init__.py
lib/vsc/mympingpong/__init__.py
lib/vsc/mympingpong/pairs.py
lib/vsc/mympingpong/pingpongers.py
lib/vsc/mympingpong/tools.py