Metadata-Version: 2.1
Name: mympingpong
Version: 0.8.1
Summary: UNKNOWN
Home-page: https://github.com/hpcugent/mympingpong
Author: Stijn De Weirdt;Kenneth Hoste
Author-email: stijn.deweirdt@ugent.be, kenneth.hoste@ugent.be
Maintainer: Stijn De Weirdt;Kenneth Hoste
Maintainer-email: stijn.deweirdt@ugent.be, kenneth.hoste@ugent.be
License: GPLv2
Platform: UNKNOWN
Classifier: License :: OSI Approved :: GNU General Public License v2 (GPLv2)
